_dlplan.cpython-38-x86_64-linux-gnu.so
dlplan-0.3.29.dist-info/top_level.txt
dlplan-0.3.29.dist-info/RECORD
dlplan-0.3.29.dist-info/LICENSE.md
dlplan-0.3.29.dist-info/METADATA
dlplan-0.3.29.dist-info/WHEEL
dlplan/__init__.py
dlplan/generator/__init__.py
dlplan/generator/__init__.pyi
dlplan/state_space/__init__.py
dlplan/state_space/__init__.pyi
dlplan/policy/__init__.py
dlplan/policy/__init__.pyi
dlplan/core/__init__.py
dlplan/core/__init__.pyi
dlplan/novelty/__init__.py
dlplan/novelty/__init__.pyi
dlplan.libs/libstdc++-496613c0.so.6.0.32
dlplan.libs/libgcc_s-a3a07607.so.1
