Metadata-Version: 2.1
Name: dlplan
Version: 0.3.29
Summary: A library for using description logics features in planning
Home-page: https://github.com/rleap-project/dlplan
Author: Dominik Drexler, Jendrik Seipp and Guillem Francès
Author-email: dominik.drexler@liu.se
License-File: LICENSE.md
Requires-Dist: state-space-generator==0.1.9
Requires-Dist: cmake>=3.21
Provides-Extra: test
Requires-Dist: pytest; extra == "test"
